truckfactor/__init__.py
truckfactor/compute.py
truckfactor/evo_log_to_csv.py
truckfactor/repair_git_move.py
truckfactor-0.3.2.dist-info/LICENSE
truckfactor-0.3.2.dist-info/METADATA
truckfactor-0.3.2.dist-info/WHEEL
truckfactor-0.3.2.dist-info/entry_points.txt
truckfactor-0.3.2.dist-info/RECORD
